marketing_attribution_models/MAM.py
marketing_attribution_models/__init__.py
marketing_attribution_models-1.0.10.dist-info/LICENSE
marketing_attribution_models-1.0.10.dist-info/METADATA
marketing_attribution_models-1.0.10.dist-info/WHEEL
marketing_attribution_models-1.0.10.dist-info/top_level.txt
marketing_attribution_models-1.0.10.dist-info/RECORD
